optotrak/__init__.py
optotrak/__version__
optotrak-0.1.0.dist-info/LICENSE
optotrak-0.1.0.dist-info/METADATA
optotrak-0.1.0.dist-info/WHEEL
optotrak-0.1.0.dist-info/top_level.txt
optotrak-0.1.0.dist-info/RECORD
