Metadata-Version: 2.1
Name: optotrak
Version: 0.1.0
Summary: Load data from NDI Optotrak sensors.
Home-page: https://github.com/otaithleigh/optotrak
Author: Peter Talley
Author-email: ptalley2@vols.utk.edu
License: MIT
Platform: UNKNOWN
Requires-Python: >=3.7
License-File: LICENSE
Requires-Dist: numpy
Requires-Dist: pandas
